lifted/__init__.py
lifted/py.typed
lifted-0.2.6.dist-info/LICENSE
lifted-0.2.6.dist-info/METADATA
lifted-0.2.6.dist-info/WHEEL
lifted-0.2.6.dist-info/top_level.txt
lifted-0.2.6.dist-info/RECORD
