Metadata-Version: 2.1
Name: lifted
Version: 0.2.6
Summary: A minimal parser combinator library.
Home-page: https://github.com/wbbradley/python-parsing
Author: William Bradley
Author-email: williambbradley@gmail.com
License: UNKNOWN
Platform: UNKNOWN
Classifier: Programming Language :: Python :: 3
Classifier: License :: OSI Approved :: MIT License
Classifier: Operating System :: OS Independent
License-File: LICENSE
